{"type":"FeatureCollection","features":[{"type":"Feature","properties":{"volume":1,"part":"2b","number":"47-v1","title":"Berry Head bearing North 21 East Distant 6 Miles & White Head Island North 63 East Distant 11 Miles","url":"http://maps.bpl.org/id/15150","date":1775,"state":"1?"},"geometry":{"type":"Point","coordinates":[-61.305427551269524,45.170177929417974]}}]}