{"type":"FeatureCollection","features":[{"type":"Feature","properties":{"volume":1,"part":"1a","number":43,"title":" Mechios River near the Mills; A Sketch of Mechios Mills, July 31, 1777 (2 views)","url":"http://maps.bpl.org/id/15113","date":1777},"geometry":{"type":"Point","coordinates":[-67.44403839111328,44.71697752292507]}}]}